Ghaflankoo_shamsi/Ghaflankoo_shamsi.py
Ghaflankoo_shamsi/__init__.py
tests/__init__.py
tests/test_ml.py
Ghaflankoo_shamsi-1.0.0.dist-info/METADATA
Ghaflankoo_shamsi-1.0.0.dist-info/WHEEL
Ghaflankoo_shamsi-1.0.0.dist-info/top_level.txt
Ghaflankoo_shamsi-1.0.0.dist-info/RECORD
