Metadata-Version: 2.1
Name: Ghaflankoo_shamsi
Version: 1.0.0
Summary: Jalali datetime convert for python
Home-page: https://github.com/mehdigh125/Ghaflanko_shamsi.git
Author: mehdi ghaffari moghaddam
Author-email: mehdi.ghaffari.moghaddam@gmail.com
Classifier: Programming Language :: Python :: 3
Classifier: License :: OSI Approved :: MIT License
Classifier: Operating System :: OS Independent
Requires-Python: >=3.6
Requires-Dist: click
